odoo/addons/base_business_document_import/README.rst
odoo/addons/base_business_document_import/__init__.py
odoo/addons/base_business_document_import/__manifest__.py
odoo/addons/base_business_document_import/i18n/base_business_document_import.pot
odoo/addons/base_business_document_import/i18n/cs_CZ.po
odoo/addons/base_business_document_import/i18n/fr.po
odoo/addons/base_business_document_import/i18n/nl.po
odoo/addons/base_business_document_import/models/__init__.py
odoo/addons/base_business_document_import/models/business_document_import.py
odoo/addons/base_business_document_import/readme/CONTRIBUTORS.rst
odoo/addons/base_business_document_import/readme/DESCRIPTION.rst
odoo/addons/base_business_document_import/static/description/icon.png
odoo/addons/base_business_document_import/static/description/index.html
odoo/addons/base_business_document_import/tests/__init__.py
odoo/addons/base_business_document_import/tests/test_business_document_import.py
odoo13_addon_base_business_document_import-13.0.2.1.1.dist-info/METADATA
odoo13_addon_base_business_document_import-13.0.2.1.1.dist-info/WHEEL
odoo13_addon_base_business_document_import-13.0.2.1.1.dist-info/top_level.txt
odoo13_addon_base_business_document_import-13.0.2.1.1.dist-info/RECORD
