Metadata-Version: 2.1
Name: odoo13-addon-base-business-document-import
Version: 13.0.2.1.1
Summary: Provides technical tools to import sale orders or supplier invoices
Home-page: https://github.com/OCA/edi
Author: Akretion, Nicolas JEUDY, Odoo Community Association (OCA)
Author-email: support@odoo-community.org
License: AGPL-3
Platform: UNKNOWN
Classifier: Programming Language :: Python
Classifier: Framework :: Odoo
Classifier: Framework :: Odoo :: 13.0
Classifier: License :: OSI Approved :: GNU Affero General Public License v3
Requires-Python: >=3.5
Requires-Dist: odoo13-addon-account-tax-unece
Requires-Dist: odoo13-addon-uom-unece
Requires-Dist: odoo (<13.1dev,>=13.0a)
